{
  "question": {
    "Q": "Did the pain start suddenly?",
    "Yes": {
      "question": {
        "Q": "Did the pain follow a fall or other injury to your back?",
        "Yes": {
          "question": {
            "Q": "Have you noticed one or more of the following symptoms?\n\u2022 Loss of bladder or bowel control\n\u2022 Difficulty moving a limb\n\u2022 Numbness or tingling in a limb",
            "Yes": {
              "question": {
                "Q": "EMERGENCY: Get medical help now! Call 123 or your local emergency number or have someone take you to the nearest hospital emergency department. You may have damaged your spinal cord.",
                "Yes": {},
                "No": {},
                "diagnosis": ["SPINAL CORD INJURY"]
              }
            },
            "No": {
              "question": {
                "Q": "See your doctor if the pain is severe or lasts more than 3 days. Your backache is probably caused by bruising or a muscle spasm.",
                "Yes": {},
                "No": {},
                "diagnosis": ["NONSPECIFIC BACKACHE"]
              }
            },
            "diagnosis": []
          }
        },
        "No": {
          "question": {
            "Q": "Have you lifted something heavy recently, exercised strenuously, or otherwise strained your back?",
            "Yes": {
              "question": {
                "Q": "Does the pain shoot down the back of your leg?",
                "Yes": {
                  "question": {
                    "Q": "See your doctor. You probably have sciatica (pressure on the sciatic nerve) caused by a PROLAPSED DISK.",
                    "Yes": {},
                    "No": {},
                    "diagnosis": ["PROLAPSED DISK"]
                  }
                },
                "No": {
                  "question": {
                    "Q": "Is the pain mainly in the small of your back?",
                    "Yes": {
                      "question": {
                        "Q": "You probably have low back pain from strain. You could have OSTEOARTHRITIS.",
                        "Yes": {},
                        "No": {},
                        "diagnosis": ["OSTEOARTHRITIS"]
                      }
                    },
                    "No": {
                      "question": {
                        "Q": "Are you a woman over age 60 and have you recently spent several weeks in bed or in a wheelchair?",
                        "Yes": {
                          "question": {
                            "Q": "Do you have a sharp pain in one area of your spine?",
                            "Yes": {
                              "question": {
                                "Q": "See a doctor immediately. You may have a crushed vertebra (compression fracture) as a result of OSTEOPOROSIS.",
                                "Yes": {},
                                "No": {},
                                "diagnosis": ["OSTEOPOROSIS"]
                              }
                            },
                            "No": {
                              "question": {
                                "Q": "See your doctor if the pain lasts more than 3 days. You probably strained some back muscles.",
                                "Yes": {},
                                "No": {},
                                "diagnosis": ["NONSPECIFIC BACKACHE"]
                              }
                            },
                            "diagnosis": []
                          }
                        },
                        "No": {
                          "question": {
                            "Q": "See your doctor if the pain lasts more than 3 days. You probably strained some back muscles.",
                            "Yes": {},
                            "No": {},
                            "diagnosis": ["NONSPECIFIC BACKACHE"]
                          }
                        },
                        "diagnosis": []
                      }
                    },
                    "diagnosis": []
                  }
                },
                "diagnosis": []
              }
            },
            "No": {
              "question": {
                "Q": "Are you a woman over age 60 and have you recently spent several weeks in bed or in a wheelchair?",
                "Yes": {
                  "question": {
                    "Q": "Do you have a sharp pain in one area of your spine?",
                    "Yes": {
                      "question": {
                        "Q": "See a doctor immediately. You may have a crushed vertebra (compression fracture) as a result of OSTEOPOROSIS.",
                        "Yes": {},
                        "No": {},
                        "diagnosis": ["OSTEOPOROSIS"]
                      }
                    },
                    "No": {
                      "question": {
                        "Q": "See your doctor if the pain lasts more than 3 days. You probably strained some back muscles.",
                        "Yes": {},
                        "No": {},
                        "diagnosis": ["NONSPECIFIC BACKACHE"]
                      }
                    },
                    "diagnosis": []
                  }
                },
                "No": {
                  "question": {
                    "Q": "See your doctor if the pain lasts more than 3 days. You probably strained some back muscles.",
                    "Yes": {},
                    "No": {},
                    "diagnosis": ["NONSPECIFIC BACKACHE"]
                  }
                },
                "diagnosis": []
              }
            },
            "diagnosis": []
          }
        },
        "diagnosis": []
      }
    },
    "No": {
      "question": {
        "Q": "Is your temperature 100 \u2109 (37.8 \u2103 ) or higher?",
        "Yes": {
          "question": {
            "Q": "See a doctor immediately. You may have a serious kidney infection such as ACUTE PYELONEPHRITIS or you may have an EPIDURAL ABSCESS.",
            "Yes": {},
            "No": {},
            "diagnosis": ["ACUTE PYELONEPHRITIS", "EPIDURAL ABSCESS"]
          }
        },
        "No": {
          "question": {
            "Q": "Is the pain mainly in the lower part of your back?",
            "Yes": {
              "question": {
                "Q": "Does the pain shoot down the back of your leg?",
                "Yes": {
                  "question": {
                    "Q": "You probably have sciatica (pressure on the sciatic nerve) caused by a PROLAPSED DISK.",
                    "Yes": {},
                    "No": {},
                    "diagnosis": ["PROLAPSED DISK"]
                  }
                },
                "No": {
                  "question": {
                    "Q": "Are you more than 4 months pregnant?",
                    "Yes": {
                      "question": {
                        "Q": "Lower backache is common during pregnancy.",
                        "Yes": {},
                        "No": {},
                        "diagnosis": ["BACK PAIN"]
                      }
                    },
                    "No": {
                      "question": {
                        "Q": "Are you overweight according to the body mass index (BMI)?",
                        "Yes": {
                          "question": {
                            "Q": "Carrying too much weight can strain your back muscles. Losing weight will ease some of the strain on your back.",
                            "Yes": {},
                            "No": {},
                            "diagnosis": []
                          }
                        },
                        "No": {
                          "question": {
                            "Q": "Are you over age 50, and is the pain worse after a period of inactivity (such as after getting up in the morning)?",
                            "Yes": {
                              "question": {
                                "Q": "Do you have pain in other joints, including the hip, knee, or ankle?",
                                "Yes": {
                                  "question": {
                                    "Q": "You may have OSTEOARTHRITIS (p. 996), or you may be doing something that hurts your back.",
                                    "Yes": {},
                                    "No": {},
                                    "diagnosis": []
                                  }
                                },
                                "No": {
                                  "question": {
                                    "Q": "Could your back be strained by your working conditions (such as sitting in a chair the wrong height for your desk or hunching over while looking at your computer screen)?",
                                    "Yes": {
                                      "question": {
                                        "Q": "Backache often results from such strain and poor posture.",
                                        "Yes": {},
                                        "No": {},
                                        "diagnosis": ["NONSPECIFIC BACKACHE"]
                                      }
                                    },
                                    "No": {
                                      "question": {
                                        "Q": "See your doctor if you are unable to make a diagnosis from this chat.",
                                        "Yes": {},
                                        "No": {},
                                        "diagnosis": []
                                      }
                                    },
                                    "diagnosis": []
                                  }
                                },
                                "diagnosis": []
                              }
                            },
                            "No": {
                              "question": {
                                "Q": "Could your back be strained by your working conditions (such as sitting in a chair the wrong height for your desk or hunching over while looking at your computer screen)?",
                                "Yes": {
                                  "question": {
                                    "Q": "Backache often results from such strain and poor posture.",
                                    "Yes": {},
                                    "No": {},
                                    "diagnosis": ["NONSPECIFIC BACKACHE"]
                                  }
                                },
                                "No": {
                                  "question": {
                                    "Q": "See your doctor if you are unable to make a diagnosis from this chat.",
                                    "Yes": {},
                                    "No": {},
                                    "diagnosis": []
                                  }
                                },
                                "diagnosis": []
                              }
                            },
                            "diagnosis": []
                          }
                        },
                        "diagnosis": []
                      }
                    },
                    "diagnosis": []
                  }
                },
                "diagnosis": []
              }
            },
            "No": {
              "question": {
                "Q": "Are you over age 50, and is the pain worse after a period of inactivity (such as after getting up in the morning)?",
                "Yes": {
                  "question": {
                    "Q": "Do you have pain in other joints, including the hip, knee, or ankle?",
                    "Yes": {
                      "question": {
                        "Q": "You may have OSTEOARTHRITIS (p. 996), or you may be doing something that hurts your back.",
                        "Yes": {},
                        "No": {},
                        "diagnosis": []
                      }
                    },
                    "No": {
                      "question": {
                        "Q": "Could your back be strained by your working conditions (such as sitting in a chair the wrong height for your desk or hunching over while looking at your computer screen)?",
                        "Yes": {
                          "question": {
                            "Q": "Backache often results from such strain and poor posture.",
                            "Yes": {},
                            "No": {},
                            "diagnosis": ["NONSPECIFIC BACKACHE"]
                          }
                        },
                        "No": {
                          "question": {
                            "Q": "See your doctor if you are unable to make a diagnosis from this chat.",
                            "Yes": {},
                            "No": {},
                            "diagnosis": []
                          }
                        },
                        "diagnosis": []
                      }
                    },
                    "diagnosis": []
                  }
                },
                "No": {
                  "question": {
                    "Q": "Could your back be strained by your working conditions (such as sitting in a chair the wrong height for your desk or hunching over while looking at your computer screen)?",
                    "Yes": {
                      "question": {
                        "Q": "Backache often results from such strain and poor posture.",
                        "Yes": {},
                        "No": {},
                        "diagnosis": ["NONSPECIFIC BACKACHE"]
                      }
                    },
                    "No": {
                      "question": {
                        "Q": "See your doctor if you are unable to make a diagnosis from this chat.",
                        "Yes": {},
                        "No": {},
                        "diagnosis": []
                      }
                    },
                    "diagnosis": []
                  }
                },
                "diagnosis": []
              }
            },
            "diagnosis": []
          }
        },
        "diagnosis": []
      }
    },
    "diagnosis": []
  }
}
